{
    "fluentMethods": true,
    "relationships": [],
    "fields": [
        {
            "fieldName": "dwqc",
            "fieldType": "String",
            "fieldValidateRules": [
                "required",
                "maxlength"
            ],
            "fieldValidateRulesMaxlength": 60
        },
        {
            "fieldName": "hxcpmc",
            "fieldType": "String",
            "fieldValidateRules": [
                "required",
                "maxlength"
            ],
            "fieldValidateRulesMaxlength": 120
        },
        {
            "fieldName": "zztjdw",
            "fieldType": "String"
        },
        {
            "fieldName": "dwhgrdz",
            "fieldType": "String",
            "fieldValidateRules": [
                "required",
                "maxlength"
            ],
            "fieldValidateRulesMaxlength": 100
        },
        {
            "fieldName": "szqylx",
            "fieldType": "String",
            "fieldValidateRules": [
                "required"
            ]
        },
        {
            "fieldName": "ssly",
            "fieldType": "String",
            "fieldValidateRules": [
                "required"
            ]
        },
        {
            "fieldName": "gscpjj",
            "fieldType": "String",
            "fieldValidateRules": [
                "required",
                "maxlength"
            ],
            "fieldValidateRulesMaxlength": 360
        },
        {
            "fieldName": "mbkhsc",
            "fieldType": "String",
            "fieldValidateRules": [
                "required"
            ]
        },
        {
            "fieldName": "dqzykh",
            "fieldType": "String"
        },
        {
            "fieldName": "gnwhjjx",
            "fieldType": "String",
            "fieldValidateRules": [
                "maxlength"
            ],
            "fieldValidateRulesMaxlength": 500
        },
        {
            "fieldName": "zljs",
            "fieldType": "Decision",
            "fieldValues": "YES,NO",
            "fieldValidateRules": [
                "required"
            ]
        },
        {
            "fieldName": "hxjsly",
            "fieldType": "HxjslyEnum",
            "fieldValues": "S1,S2,S3,S4,OTHER",
            "fieldValidateRules": [
                "required"
            ]
        },
        {
            "fieldName": "kjcgzh",
            "fieldType": "KjcgzhEnum",
            "fieldValues": "S1,S2,S3,OTHER",
            "fieldValidateRules": [
                "required"
            ]
        },
        {
            "fieldName": "jmlyqk",
            "fieldType": "JmlyqkEnum",
            "fieldValues": "K1,K2,K3",
            "fieldValidateRules": [
                "required"
            ]
        },
        {
            "fieldName": "jscsd",
            "javadoc": "创新",
            "fieldType": "String",
            "fieldValidateRules": [
                "maxlength"
            ],
            "fieldValidateRulesMaxlength": 120
        },
        {
            "fieldName": "jzmsylqk",
            "javadoc": "end\n创业",
            "fieldType": "String",
            "fieldValidateRules": [
                "maxlength"
            ],
            "fieldValidateRulesMaxlength": 500
        },
        {
            "fieldName": "jzysjs",
            "javadoc": "end",
            "fieldType": "String",
            "fieldValidateRules": [
                "required",
                "maxlength"
            ],
            "fieldValidateRulesMaxlength": 500
        },
        {
            "fieldName": "fzrdh",
            "fieldType": "String",
            "fieldValidateRules": [
                "required",
                "maxlength"
            ],
            "fieldValidateRulesMaxlength": 20
        },
        {
            "fieldName": "xb",
            "fieldType": "XbEnum",
            "fieldValues": "MAN,WOMAN",
            "fieldValidateRules": [
                "required"
            ]
        },
        {
            "fieldName": "lxfs",
            "fieldType": "String",
            "fieldValidateRules": [
                "required",
                "maxlength"
            ],
            "fieldValidateRulesMaxlength": 36
        },
        {
            "fieldName": "email",
            "fieldType": "String",
            "fieldValidateRules": [
                "required",
                "maxlength"
            ],
            "fieldValidateRulesMaxlength": 36
        },
        {
            "fieldName": "fzrnl",
            "fieldType": "AgeEnum",
            "fieldValues": "A1,A2,A3,A4,A5,A6,A7",
            "fieldValidateRules": [
                "required"
            ]
        },
        {
            "fieldName": "tdpjnl",
            "fieldType": "AgeEnum",
            "fieldValues": "A1,A2,A3,A4,A5,A6,A7"
        },
        {
            "fieldName": "gjrcs",
            "fieldType": "Integer",
            "fieldValidateRules": [
                "required"
            ]
        },
        {
            "fieldName": "sfgjrzgxjsqy",
            "fieldType": "Decision",
            "fieldValues": "YES,NO",
            "fieldValidateRules": [
                "required"
            ]
        },
        {
            "fieldName": "tdysjs",
            "fieldType": "String",
            "fieldValidateRules": [
                "required",
                "maxlength"
            ],
            "fieldValidateRulesMaxlength": 500
        },
        {
            "fieldName": "xycz",
            "fieldType": "String",
            "fieldValidateRules": [
                "required",
                "maxlength"
            ],
            "fieldValidateRulesMaxlength": 24
        },
        {
            "fieldName": "wlxwhdzclx",
            "fieldType": "String",
            "fieldValidateRules": [
                "required",
                "maxlength"
            ],
            "fieldValidateRulesMaxlength": 36
        },
        {
            "fieldName": "wlxwhdzclx1",
            "fieldType": "String",
            "fieldValidateRules": [
                "maxlength"
            ],
            "fieldValidateRulesMaxlength": 100
        },
        {
            "fieldName": "sfxyxc",
            "fieldType": "String",
            "fieldValidateRules": [
                "maxlength"
            ],
            "fieldValidateRulesMaxlength": 100
        },
        {
            "fieldName": "rzjhgkfw",
            "javadoc": "创业",
            "fieldType": "RzjhgkfwEnum",
            "fieldValues": "O1,O2,O3"
        },
        {
            "fieldName": "rzmb",
            "fieldType": "RzmbEnum",
            "fieldValues": "R1,R2,R3,R4,R5,R6,R7,R8"
        },
        {
            "fieldName": "lxrzw",
            "javadoc": "end",
            "fieldType": "String",
            "fieldValidateRules": [
                "required",
                "maxlength"
            ],
            "fieldValidateRulesMaxlength": 100
        },
        {
            "fieldName": "lxdh",
            "fieldType": "String",
            "fieldValidateRules": [
                "required"
            ]
        },
        {
            "fieldName": "lxyx",
            "fieldType": "String",
            "fieldValidateRules": [
                "required",
                "maxlength"
            ],
            "fieldValidateRulesMaxlength": 60
        },
        {
            "fieldName": "lxdz",
            "fieldType": "String",
            "fieldValidateRules": [
                "required",
                "maxlength"
            ],
            "fieldValidateRulesMaxlength": 120
        },
        {
            "fieldName": "ssly1",
            "fieldType": "String",
            "fieldValidateRules": [
                "maxlength"
            ],
            "fieldValidateRulesMaxlength": 60
        },
        {
            "fieldName": "createdDate",
            "fieldType": "LocalDate",
            "fieldValidateRules": [
                "required"
            ]
        },
        {
            "fieldName": "modifiedDate",
            "fieldType": "LocalDate"
        }
    ],
    "changelogDate": "20180608234210",
    "entityTableName": "jerk_detail",
    "dto": "no",
    "pagination": "no",
    "service": "no",
    "jpaMetamodelFiltering": false,
    "angularJSSuffix": "guoyiSuffix"
}